MoodleGet/__init__.py
MoodleGet/main.py
MoodleGet-1.0.dist-info/LICENSE
MoodleGet-1.0.dist-info/METADATA
MoodleGet-1.0.dist-info/WHEEL
MoodleGet-1.0.dist-info/top_level.txt
MoodleGet-1.0.dist-info/RECORD
