Metadata-Version: 2.1
Name: MoodleGet
Version: 1.0
Summary: convenient way to get data through Moodle's API
Home-page: https://github.com/dynamyy/MoodleAPI
Author: dynamy
License: MIT
Classifier: Programming Language :: Python :: 3
Classifier: License :: OSI Approved :: MIT License
Classifier: Operating System :: OS Independent
Requires-Python: >=3.7
License-File: LICENSE
Requires-Dist: requests >=2.32.3
